heroku_connect/__init__.py
heroku_connect/admin.py
heroku_connect/apps.py
heroku_connect/checks.py
heroku_connect/conf.py
heroku_connect/contrib/__init__.py
heroku_connect/contrib/heroku_connect_health_check/__init__.py
heroku_connect/contrib/heroku_connect_health_check/apps.py
heroku_connect/contrib/heroku_connect_health_check/backends.py
heroku_connect/db/__init__.py
heroku_connect/db/backends/__init__.py
heroku_connect/db/backends/base/__init__.py
heroku_connect/db/backends/base/base.py
heroku_connect/db/backends/base/creation.py
heroku_connect/db/backends/postgis/__init__.py
heroku_connect/db/backends/postgis/base.py
heroku_connect/db/backends/postgresql/__init__.py
heroku_connect/db/backends/postgresql/base.py
heroku_connect/db/exceptions.py
heroku_connect/db/models/__init__.py
heroku_connect/db/models/base.py
heroku_connect/db/models/fields.py
heroku_connect/db/models/related.py
heroku_connect/db/router.py
heroku_connect/management/__init__.py
heroku_connect/management/commands/__init__.py
heroku_connect/management/commands/create_development_schema.py
heroku_connect/management/commands/import_mappings.py
heroku_connect/management/commands/load_remote_schema.py
heroku_connect/management/commands/makemappings.py
heroku_connect/migrations/0001_initial.py
heroku_connect/migrations/__init__.py
heroku_connect/models.py
heroku_connect/test/__init__.py
heroku_connect/test/utils.py
heroku_connect/utils.py
django_heroku_connect-6.0.0.dist-info/METADATA
django_heroku_connect-6.0.0.dist-info/WHEEL
django_heroku_connect-6.0.0.dist-info/licenses/LICENSE
django_heroku_connect-6.0.0.dist-info/RECORD
