Metadata-Version: 2.4
Name: django-heroku-connect
Version: 6.0.0
Summary: Django integration Salesforce using Heroku Connect.
License: Apache-2.0
License-File: LICENSE
Keywords: heroku,salesforce,django
Author: thermondo
Author-email: opensource@thermondo.de
Requires-Python: >=3.10,<4.0
Classifier: Development Status :: 4 - Beta
Classifier: Environment :: Console
Classifier: Framework :: Django
Classifier: Intended Audience :: Developers
Classifier: Intended Audience :: Information Technology
Classifier: License :: OSI Approved :: Apache Software License
Classifier: Operating System :: OS Independent
Classifier: Programming Language :: Python
Classifier: Programming Language :: Python :: 3
Classifier: Programming Language :: Python :: 3.10
Classifier: Programming Language :: Python :: 3.11
Classifier: Programming Language :: Python :: 3.12
Classifier: Programming Language :: Python :: 3.13
Classifier: Programming Language :: Python :: 3.14
Requires-Dist: django (>=4.2,<6.1,!=5.0.*,!=5.1.*)
Requires-Dist: django-appconf (>=1,<2)
Requires-Dist: requests (>=2,<3)
Project-URL: Documentation, https://django-heroku-connect.readthedocs.io/
Project-URL: Repository, https://github.com/thermondo/django-heroku-connect
